angem/__init__.py
angem/matrix.py
angem/rectangle.py
angem/vector2.py
angem_girvel-0.0.9.dist-info/METADATA
angem_girvel-0.0.9.dist-info/WHEEL
angem_girvel-0.0.9.dist-info/top_level.txt
angem_girvel-0.0.9.dist-info/RECORD
