Metadata-Version: 2.1
Name: angem-girvel
Version: 0.0.9
Summary: Analytic geometry library
Home-page: https://github.com/girvel/angem
Author: girvel
Author-email: widauka@yandex.ru
License: UNKNOWN
Platform: UNKNOWN
Classifier: Programming Language :: Python :: 3
Classifier: License :: OSI Approved :: MIT License
Classifier: Operating System :: OS Independent
Requires-Python: >=3.6
Requires-Dist: text-viewer-girvel
